{"nombre":"Fast Brawl","dimensiones":{"columnas":10,"filas":10},"casillas":[{"propietario":null,"tipo":"planicie","unidad":null},{"propietario":null,"tipo":"planicie","unidad":null},{"propietario":null,"tipo":"planicie","unidad":null},{"propietario":null,"tipo":"planicie","unidad":null},{"propietario":null,"tipo":"ciudad","unidad":null},{"propietario":null,"tipo":"planicie","unidad":null},{"propietario":null,"tipo":"mar","unidad":null},{"propietario":null,"tipo":"mar","unidad":null},{"propietario":null,"tipo":"arrecife","unidad":null},{"propietario":null,"tipo":"mar","unidad":null},{"propietario":null,"tipo":"planicie","unidad":null},{"propietario":null,"tipo":"planicie","unidad":{"id":"00584e54-f361-47a7-a02c-c9c7432c9511","propietario":0,"hp":100,"municiones":{"principal":6},"gasActual":40,"estado":null,"nombreUnidad":"infanteria"}},{"propietario":null,"tipo":"planicie","unidad":null},{"propietario":null,"tipo":"planicie","unidad":null},{"propietario":null,"tipo":"camino","unidad":null},{"propietario":null,"tipo":"planicie","unidad":null},{"propietario":null,"tipo":"mar","unidad":null},{"propietario":null,"tipo":"mar","unidad":null},{"propietario":null,"tipo":"mar","unidad":null},{"propietario":null,"tipo":"mar","unidad":null},{"propietario":null,"tipo":"planicie","unidad":null},{"propietario":null,"tipo":"fabrica","unidad":null},{"propietario":null,"tipo":"bosque","unidad":null},{"propietario":null,"tipo":"planicie","unidad":null},{"propietario":null,"tipo":"camino","unidad":null},{"propietario":null,"tipo":"planicie","unidad":null},{"propietario":null,"tipo":"planicie","unidad":null},{"propietario":null,"tipo":"planicie","unidad":null},{"propietario":null,"tipo":"planicie","unidad":null},{"propietario":null,"tipo":"planicie","unidad":null},{"propietario":null,"tipo":"planicie","unidad":null},{"propietario":null,"tipo":"bosque","unidad":null},{"propietario":null,"tipo":"planicie","unidad":null},{"propietario":null,"tipo":"planicie","unidad":null},{"propietario":null,"tipo":"camino","unidad":null},{"propietario":null,"tipo":"planicie","unidad":null},{"propietario":null,"tipo":"planicie","unidad":null},{"propietario":null,"tipo":"bosque","unidad":null},{"propietario":null,"tipo":"ciudad","unidad":null},{"propietario":null,"tipo":"planicie","unidad":null},{"propietario":null,"tipo":"planicie","unidad":null},{"propietario":null,"tipo":"camino","unidad":null},{"propietario":null,"tipo":"camino","unidad":null},{"propietario":null,"tipo":"camino","unidad":null},{"propietario":null,"tipo":"camino","unidad":null},{"propietario":null,"tipo":"montana","unidad":null},{"propietario":null,"tipo":"planicie","unidad":null},{"propietario":null,"tipo":"planicie","unidad":null},{"propietario":null,"tipo":"planicie","unidad":null},{"propietario":null,"tipo":"planicie","unidad":null},{"propietario":null,"tipo":"planicie","unidad":null},{"propietario":null,"tipo":"planicie","unidad":null},{"propietario":null,"tipo":"planicie","unidad":null},{"propietario":null,"tipo":"planicie","unidad":null},{"propietario":null,"tipo":"montana","unidad":null},{"propietario":null,"tipo":"camino","unidad":null},{"propietario":null,"tipo":"camino","unidad":null},{"propietario":null,"tipo":"camino","unidad":null},{"propietario":null,"tipo":"camino","unidad":null},{"propietario":null,"tipo":"planicie","unidad":null},{"propietario":null,"tipo":"planicie","unidad":null},{"propietario":null,"tipo":"ciudad","unidad":null},{"propietario":null,"tipo":"bosque","unidad":null},{"propietario":null,"tipo":"planicie","unidad":null},{"propietario":null,"tipo":"planicie","unidad":null},{"propietario":null,"tipo":"camino","unidad":null},{"propietario":null,"tipo":"planicie","unidad":null},{"propietario":null,"tipo":"planicie","unidad":null},{"propietario":null,"tipo":"bosque","unidad":null},{"propietario":null,"tipo":"planicie","unidad":null},{"propietario":null,"tipo":"planicie","unidad":null},{"propietario":null,"tipo":"planicie","unidad":null},{"propietario":null,"tipo":"planicie","unidad":null},{"propietario":null,"tipo":"planicie","unidad":null},{"propietario":null,"tipo":"planicie","unidad":null},{"propietario":null,"tipo":"camino","unidad":null},{"propietario":null,"tipo":"planicie","unidad":null},{"propietario":null,"tipo":"bosque","unidad":null},{"propietario":null,"tipo":"fabrica","unidad":null},{"propietario":null,"tipo":"planicie","unidad":null},{"propietario":null,"tipo":"mar","unidad":null},{"propietario":null,"tipo":"mar","unidad":null},{"propietario":null,"tipo":"mar","unidad":null},{"propietario":null,"tipo":"mar","unidad":null},{"propietario":null,"tipo":"planicie","unidad":null},{"propietario":null,"tipo":"camino","unidad":null},{"propietario":null,"tipo":"planicie","unidad":null},{"propietario":null,"tipo":"planicie","unidad":null},{"propietario":null,"tipo":"planicie","unidad":{"id":"5acfced9-6775-42fa-8625-9a4cf6c85013","propietario":1,"hp":100,"municiones":{"principal":6},"gasActual":40,"estado":null,"nombreUnidad":"infanteria"}},{"propietario":null,"tipo":"planicie","unidad":null},{"propietario":null,"tipo":"mar","unidad":null},{"propietario":null,"tipo":"arrecife","unidad":null},{"propietario":null,"tipo":"mar","unidad":null},{"propietario":null,"tipo":"mar","unidad":null},{"propietario":null,"tipo":"planicie","unidad":null},{"propietario":null,"tipo":"ciudad","unidad":null},{"propietario":null,"tipo":"planicie","unidad":null},{"propietario":null,"tipo":"planicie","unidad":null},{"propietario":null,"tipo":"planicie","unidad":null},{"propietario":null,"tipo":"planicie","unidad":null}]}